Metadata-Version: 2.1
Name: dzmymod
Version: 2
Summary: kk
Author: Vadim Laukonin
